backports/__init__.py
backports/os.py
backports.os-0.1.dist-info/DESCRIPTION.rst
backports.os-0.1.dist-info/METADATA
backports.os-0.1.dist-info/RECORD
backports.os-0.1.dist-info/WHEEL
backports.os-0.1.dist-info/metadata.json
backports.os-0.1.dist-info/top_level.txt
